liquer_gui/__init__.py
liquer_gui/commands.py
liquer_gui/assets/index.html
liquer_gui/assets/css/app.fb85a8e8.css
liquer_gui/assets/css/chunk-vendors.4e534170.css
liquer_gui/assets/css/chunk-vendors.d50b498d.css
liquer_gui/assets/js/app.1501a2d1.js
liquer_gui/assets/js/app.1501a2d1.js.map
liquer_gui/assets/js/app.1775f745.js
liquer_gui/assets/js/app.1775f745.js.map
liquer_gui/assets/js/app.18a5d1ca.js
liquer_gui/assets/js/app.18a5d1ca.js.map
liquer_gui/assets/js/app.26e21934.js
liquer_gui/assets/js/app.26e21934.js.map
liquer_gui/assets/js/app.276ee842.js
liquer_gui/assets/js/app.276ee842.js.map
liquer_gui/assets/js/app.2cd7e0c0.js
liquer_gui/assets/js/app.2cd7e0c0.js.map
liquer_gui/assets/js/app.2d17f237.js
liquer_gui/assets/js/app.2d17f237.js.map
liquer_gui/assets/js/app.397fee1d.js
liquer_gui/assets/js/app.397fee1d.js.map
liquer_gui/assets/js/app.3df7f627.js
liquer_gui/assets/js/app.3df7f627.js.map
liquer_gui/assets/js/app.44cf795e.js
liquer_gui/assets/js/app.44cf795e.js.map
liquer_gui/assets/js/app.4e1a38dc.js
liquer_gui/assets/js/app.4e1a38dc.js.map
liquer_gui/assets/js/app.6350bc18.js
liquer_gui/assets/js/app.6350bc18.js.map
liquer_gui/assets/js/app.6f5c6a15.js
liquer_gui/assets/js/app.6f5c6a15.js.map
liquer_gui/assets/js/app.7277e347.js
liquer_gui/assets/js/app.7277e347.js.map
liquer_gui/assets/js/app.75e72613.js
liquer_gui/assets/js/app.75e72613.js.map
liquer_gui/assets/js/app.7d11e046.js
liquer_gui/assets/js/app.7d11e046.js.map
liquer_gui/assets/js/app.7fd01d7c.js
liquer_gui/assets/js/app.7fd01d7c.js.map
liquer_gui/assets/js/app.a9f2f481.js
liquer_gui/assets/js/app.a9f2f481.js.map
liquer_gui/assets/js/app.aaa420da.js
liquer_gui/assets/js/app.aaa420da.js.map
liquer_gui/assets/js/app.abc947c3.js
liquer_gui/assets/js/app.abc947c3.js.map
liquer_gui/assets/js/app.b33f0def.js
liquer_gui/assets/js/app.b33f0def.js.map
liquer_gui/assets/js/app.b33f9660.js
liquer_gui/assets/js/app.b33f9660.js.map
liquer_gui/assets/js/app.c477e36e.js
liquer_gui-0.2.0.dist-info/METADATA
liquer_gui-0.2.0.dist-info/WHEEL
liquer_gui-0.2.0.dist-info/top_level.txt
liquer_gui-0.2.0.dist-info/RECORD
