Metadata-Version: 2.1
Name: liquer-gui
Version: 0.2.0
Summary: LiQuer GUI - user interface for LiQuer.
Home-page: https://github.com/orest-d/liquer-gui
Author: Orest Dubay
Author-email: orest3.dubay@gmail.com
License: UNKNOWN
Platform: UNKNOWN
Classifier: Programming Language :: Python :: 3
Classifier: License :: OSI Approved :: MIT License
Classifier: Operating System :: OS Independent
Requires-Dist: Flask
Requires-Dist: liquer-framework
